control_unit_lut.v
// Notation Simplification for Control unit LUT Commands

// I type ops
`define BNE      6'd05
`define LW       6'd35
`define SW       6'd43

// J type ops
`define J        6'd2
`define JAL      6'd3

// R Type ops
`define R_type   6'd0
// R type functs
`define JR_c       6'd8
`define XOR_c      6'd38
`define ADD_c      6'd32
`define SUB_c      6'd34
`define SLT_c      6'd42

// ALU Translation
`define ADD  3'd0
`define SUB  3'd1
`define XOR  3'd2
`define SLT  3'd3
`define AND  3'd4
`define NAND 3'd5
`define NOR  3'd6
`define OR   3'd7


module LUTcaller // Converts the commands to a more convenient format
(
    output reg       WrEn_Reg,
    output reg       WrEn_DM,
    output reg[1:0]  WrAddr_Reg_Mux,
    output reg       ALU_input,
    output reg[5:0]  ALUcommand,
    output reg[1:0]  Reg_Data_Src_Mux,
    output reg       Jump,
    output reg[1:0]  Jump_Target_Mux,
    output reg       Branch,
    input[5:0]       controlUnitCommand,
    input[5:0]       funct
);

    wire       WrEn_Reg1;
    wire       WrEn_DM1;
    wire[1:0]  WrAddr_Reg_Mux1;
    wire       ALU_input1;
    wire[5:0]  ALUcommand1;
    wire[1:0]  Reg_Data_Src_Mux1;
    wire       Jump1;
    wire[1:0]  Jump_Target_Mux1;
    wire       Branch1;

    wire       WrEn_Reg2;
    wire       WrEn_DM2;
    wire[1:0]  WrAddr_Reg_Mux2;
    wire       ALU_input2;
    wire[5:0]  ALUcommand2;
    wire[1:0]  Reg_Data_Src_Mux2;
    wire       Jump2;
    wire[1:0]  Jump_Target_Mux2;
    wire       Branch2;

    controlUnitLUT  lut_ctrl(WrEn_Reg1, WrEn_DM1, WrAddr_Reg_Mux1, ALU_input1, ALUcommand1, 
                            Reg_Data_Src_Mux1, Jump1, Jump_Target_Mux1, Branch1, controlUnitCommand, funct);

    R_type_LUT      R_ctrl(WrEn_Reg2, WrEn_DM2, WrAddr_Reg_Mux2, ALU_input2, ALUcommand2, 
                            Reg_Data_Src_Mux2, Jump2, Jump_Target_Mux2, Branch2, funct);

    always@* begin
        if (controlUnitCommand == 6'd0) begin
            WrEn_Reg <= WrEn_Reg2;
            WrEn_DM <= WrEn_DM2;
            WrAddr_Reg_Mux <= WrAddr_Reg_Mux2;
            ALU_input <= ALU_input2;
            ALUcommand <= ALUcommand2;
            Reg_Data_Src_Mux <= Reg_Data_Src_Mux2;
            Jump <= Jump2;
            Jump_Target_Mux <= Jump_Target_Mux2;
            Branch <= Branch2;     
        end
        else begin
            WrEn_Reg <= WrEn_Reg1;
            WrEn_DM <= WrEn_DM1;
            WrAddr_Reg_Mux <= WrAddr_Reg_Mux1;
            ALU_input <= ALU_input1;
            ALUcommand <= ALUcommand1;
            Reg_Data_Src_Mux <= Reg_Data_Src_Mux1;
            Jump <= Jump1;
            Jump_Target_Mux <= Jump_Target_Mux1;
            Branch <= Branch1;      
        end
    end

endmodule


module controlUnitLUT // Converts the commands to a more convenient format
(
    output reg       WrEn_Reg,
    output reg       WrEn_DM,
    output reg[1:0]  WrAddr_Reg_Mux,
    output reg       ALU_input,
    output reg[5:0]  ALUcommand,
    output reg[1:0]  Reg_Data_Src_Mux,
    output reg       Jump,
    output reg[1:0]  Jump_Target_Mux,
    output reg       Branch,
    input[5:0]       controlUnitCommand,
    input[5:0]       funct
);

    always @(controlUnitCommand) begin
      case (controlUnitCommand)
            `BNE:      begin WrEn_Reg = 0; WrEn_DM = 0; WrAddr_Reg_Mux = 0; ALU_input = 1; ALUcommand = `SUB;    Reg_Data_Src_Mux = 0;      Jump = 0; Jump_Target_Mux = 2'd2; Branch = 1; end
            `LW:       begin WrEn_Reg = 1; WrEn_DM = 0; WrAddr_Reg_Mux = 0; ALU_input = 0; ALUcommand = `ADD;    Reg_Data_Src_Mux = 0;      Jump = 0; Jump_Target_Mux = 0; Branch = 0; end
            `SW:       begin WrEn_Reg = 0; WrEn_DM = 1; WrAddr_Reg_Mux = 0; ALU_input = 0; ALUcommand = `ADD;    Reg_Data_Src_Mux = 0;      Jump = 0; Jump_Target_Mux = 0; Branch = 0; end
            `J:        begin WrEn_Reg = 0; WrEn_DM = 0; WrAddr_Reg_Mux = 0; ALU_input = 0; ALUcommand = `ADD;    Reg_Data_Src_Mux = 0;      Jump = 1; Jump_Target_Mux = 1; Branch = 0; end
            `JAL:      begin WrEn_Reg = 1; WrEn_DM = 0; WrAddr_Reg_Mux = 0; ALU_input = 0; ALUcommand = `ADD;    Reg_Data_Src_Mux = 2'd2;   Jump = 1; Jump_Target_Mux = 1; Branch = 0; end
       endcase
    end
endmodule

module R_type_LUT // Converts the commands to a more convenient format
(
    output reg       WrEn_Reg,
    output reg       WrEn_DM,
    output reg[1:0]  WrAddr_Reg_Mux,
    output reg       ALU_input,
    output reg[5:0]  ALUcommand,
    output reg[1:0]  Reg_Data_Src_Mux,
    output reg       Jump,
    output reg[1:0]  Jump_Target_Mux,
    output reg       Branch,
    input[5:0]       funct
);

    always @(funct) begin
      case (funct)
            `JR_c:      begin WrEn_Reg = 0; WrEn_DM = 0; WrAddr_Reg_Mux = 0; ALU_input = 0; ALUcommand = 6'd0;    Reg_Data_Src_Mux = 0;      Jump = 1; Jump_Target_Mux = 1; Branch = 0; end
            `XOR_c:     begin WrEn_Reg = 1; WrEn_DM = 0; WrAddr_Reg_Mux = 1; ALU_input = 1; ALUcommand = `XOR;    Reg_Data_Src_Mux = 1;      Jump = 0; Jump_Target_Mux = 0; Branch = 0; end
            `ADD_c:     begin WrEn_Reg = 1; WrEn_DM = 0; WrAddr_Reg_Mux = 1; ALU_input = 1; ALUcommand = `ADD;    Reg_Data_Src_Mux = 1;      Jump = 0; Jump_Target_Mux = 0; Branch = 0; end
            `SUB_c:     begin WrEn_Reg = 1; WrEn_DM = 0; WrAddr_Reg_Mux = 1; ALU_input = 1; ALUcommand = `SUB;    Reg_Data_Src_Mux = 1;      Jump = 0; Jump_Target_Mux = 0; Branch = 0; end
            `SLT_c:     begin WrEn_Reg = 1; WrEn_DM = 0; WrAddr_Reg_Mux = 1; ALU_input = 1; ALUcommand = `SLT;    Reg_Data_Src_Mux = 1;      Jump = 0; Jump_Target_Mux = 0; Branch = 0; end
       endcase
    end
endmodule

control_unit_lut.t.v
//------------------------------------------------------------------------
// Control unit LUT test bnch
//------------------------------------------------------------------------
`timescale 1ns / 1ps

`include "control_unit_lut.v"

module testlut();

    wire        WrEn_Reg;
    wire        WrEn_DM;
    wire[1:0]   WrAddr_Reg_Mux;
    wire        ALU_input;
    wire[5:0]   ALUcommand;
    wire[1:0]   Reg_Data_Src_Mux;
    wire        Jump;
    wire[1:0]   Jump_Target_Mux;
    wire        Branch;
    reg[5:0]    controlUnitCommand;
    reg[5:0]    funct;


    LUTcaller dut(WrEn_Reg, WrEn_DM, WrAddr_Reg_Mux,
                   ALU_input, ALUcommand, Reg_Data_Src_Mux,
                   Jump, Jump_Target_Mux, Branch, controlUnitCommand,
                   funct);

    initial begin
    	// Your Test Code
        $dumpfile("controlUnitLUT.vcd");
        $dumpvars();

        #2
        // I type command testing
        controlUnitCommand = 6'd05; #0 //bne
        #2
        controlUnitCommand = 6'd35; #2 //lw
        controlUnitCommand = 6'd43; #2 //sw

        // J type testing
        controlUnitCommand = 6'd02; #2 //j
        controlUnitCommand = 6'd03; #2 //jal

        // R type testing
        controlUnitCommand = 6'd00; #2 //r type
        
        // R type funct testing
        funct = 6'd38; #2                //xor
        funct = 6'd32; #2                //add
        funct = 6'd34; #2                //sub
        funct = 6'd42; #2                //slt  
        funct = 6'd8;  #2                //jr   
        $finish;
    end

endmodule

controlUnitLUT.vcd
$date
	Sun Nov 13 22:10:33 2016
$end
$version
	Icarus Verilog
$end
$timescale
	1ps
$end
$scope module testlut $end
$var wire 1 ! ALU_input $end
$var wire 6 " ALUcommand [5:0] $end
$var wire 1 # Branch $end
$var wire 1 $ Jump $end
$var wire 2 % Jump_Target_Mux [1:0] $end
$var wire 2 & Reg_Data_Src_Mux [1:0] $end
$var wire 2 ' WrAddr_Reg_Mux [1:0] $end
$var wire 1 ( WrEn_DM $end
$var wire 1 ) WrEn_Reg $end
$var reg 6 * controlUnitCommand [5:0] $end
$var reg 6 + funct [5:0] $end
$scope module dut $end
$var wire 1 , ALU_input1 $end
$var wire 1 - ALU_input2 $end
$var wire 6 . ALUcommand1 [5:0] $end
$var wire 6 / ALUcommand2 [5:0] $end
$var wire 1 0 Branch1 $end
$var wire 1 1 Branch2 $end
$var wire 1 2 Jump1 $end
$var wire 1 3 Jump2 $end
$var wire 2 4 Jump_Target_Mux1 [1:0] $end
$var wire 2 5 Jump_Target_Mux2 [1:0] $end
$var wire 2 6 Reg_Data_Src_Mux1 [1:0] $end
$var wire 2 7 Reg_Data_Src_Mux2 [1:0] $end
$var wire 2 8 WrAddr_Reg_Mux1 [1:0] $end
$var wire 2 9 WrAddr_Reg_Mux2 [1:0] $end
$var wire 1 : WrEn_DM1 $end
$var wire 1 ; WrEn_DM2 $end
$var wire 1 < WrEn_Reg1 $end
$var wire 1 = WrEn_Reg2 $end
$var wire 6 > controlUnitCommand [5:0] $end
$var wire 6 ? funct [5:0] $end
$var reg 1 @ ALU_input $end
$var reg 6 A ALUcommand [5:0] $end
$var reg 1 B Branch $end
$var reg 1 C Jump $end
$var reg 2 D Jump_Target_Mux [1:0] $end
$var reg 2 E Reg_Data_Src_Mux [1:0] $end
$var reg 2 F WrAddr_Reg_Mux [1:0] $end
$var reg 1 G WrEn_DM $end
$var reg 1 H WrEn_Reg $end
$scope module lut_ctrl $end
$var wire 6 I controlUnitCommand [5:0] $end
$var wire 6 J funct [5:0] $end
$var reg 1 K ALU_input $end
$var reg 6 L ALUcommand [5:0] $end
$var reg 1 M Branch $end
$var reg 1 N Jump $end
$var reg 2 O Jump_Target_Mux [1:0] $end
$var reg 2 P Reg_Data_Src_Mux [1:0] $end
$var reg 2 Q WrAddr_Reg_Mux [1:0] $end
$var reg 1 R WrEn_DM $end
$var reg 1 S WrEn_Reg $end
$upscope $end
$scope module R_ctrl $end
$var wire 6 T funct [5:0] $end
$var reg 1 U ALU_input $end
$var reg 6 V ALUcommand [5:0] $end
$var reg 1 W Branch $end
$var reg 1 X Jump $end
$var reg 2 Y Jump_Target_Mux [1:0] $end
$var reg 2 Z Reg_Data_Src_Mux [1:0] $end
$var reg 2 [ WrAddr_Reg_Mux [1:0] $end
$var reg 1 \ WrEn_DM $end
$var reg 1 ] WrEn_Reg $end
$upscope $end
$upscope $end
$upscope $end
$enddefinitions $end
#0
$dumpvars
x]
x\
bx [
bx Z
bx Y
xX
xW
bx V
xU
bx T
xS
xR
bx Q
bx P
bx O
xN
xM
bx L
xK
bx J
bx I
xH
xG
bx F
bx E
bx D
xC
xB
bx A
x@
bx ?
bx >
x=
x<
x;
x:
bx 9
bx 8
bx 7
bx 6
bx 5
bx 4
x3
x2
x1
x0
bx /
bx .
x-
x,
bx +
bx *
x)
x(
bx '
bx &
bx %
x$
x#
bx "
x!
$end
#2000
1B
1#
b10 D
b10 %
0C
0$
b0 E
b0 &
b1 A
b1 "
1@
1!
b0 F
b0 '
0G
0(
0H
0)
1M
10
b10 O
b10 4
0N
02
b0 P
b0 6
b1 L
b1 .
1K
1,
b0 Q
b0 8
0R
0:
0S
0<
b101 *
b101 >
b101 I
#4000
0B
0#
b0 D
b0 %
b0 A
b0 "
0@
0!
1H
1)
0M
00
b0 O
b0 4
b0 L
b0 .
0K
0,
1S
1<
b100011 *
b100011 >
b100011 I
#6000
1G
1(
0H
0)
1R
1:
0S
0<
b101011 *
b101011 >
b101011 I
#8000
b1 D
b1 %
1C
1$
0G
0(
b1 O
b1 4
1N
12
0R
0:
b10 *
b10 >
b10 I
#10000
b10 E
b10 &
1H
1)
b10 P
b10 6
1S
1<
b11 *
b11 >
b11 I
#12000
xB
x#
bx D
bx %
xC
x$
bx E
bx &
bx A
bx "
x@
x!
bx F
bx '
xG
x(
xH
x)
b0 *
b0 >
b0 I
#14000
0B
0#
b0 D
b0 %
0C
0$
b1 E
b1 &
b10 A
b10 "
1@
1!
b1 F
b1 '
0G
0(
1H
1)
0W
01
b0 Y
b0 5
0X
03
b1 Z
b1 7
b10 V
b10 /
1U
1-
b1 [
b1 9
0\
0;
1]
1=
b100110 +
b100110 ?
b100110 J
b100110 T
#16000
b0 A
b0 "
b0 V
b0 /
b100000 +
b100000 ?
b100000 J
b100000 T
#18000
b1 A
b1 "
b1 V
b1 /
b100010 +
b100010 ?
b100010 J
b100010 T
#20000
b11 A
b11 "
b11 V
b11 /
b101010 +
b101010 ?
b101010 J
b101010 T
#22000
b1 D
b1 %
1C
1$
b0 E
b0 &
b0 A
b0 "
0@
0!
b0 F
b0 '
0H
0)
b1 Y
b1 5
1X
13
b0 Z
b0 7
b0 V
b0 /
0U
0-
b0 [
b0 9
0]
0=
b1000 +
b1000 ?
b1000 J
b1000 T
