control_unit_lut.v
// Notation Simplification for Control unit LUT Commands

// I type ops
`define BNE      6'd05
`define LW       6'd35
`define SW       6'd43
`define XOR_c    6'd14

// J type ops
`define J        6'd2
`define JAL      6'd3

// R Type ops
`define R_type   6'd0
// R type functs
`define JR_c       6'd8
`define ADD_c      6'd32
`define SUB_c      6'd34
`define SLT_c      6'd42

// ALU Translation
`define ADD  3'd0
`define SUB  3'd1
`define XOR  3'd2
`define SLT  3'd3
`define AND  3'd4
`define NAND 3'd5
`define NOR  3'd6
`define OR   3'd7


module LUTcaller // Converts the commands to a more convenient format
(
    output reg       WrEn_Reg,
    output reg       WrEn_DM,
    output reg[1:0]  WrAddr_Reg_Mux,
    output reg       ALU_input,
    output reg[2:0]  ALUcommand,
    output reg[1:0]  Reg_Data_Src_Mux,
    output reg       JumpR,
    output reg       Jump_Target_Mux,
    output reg       Branch,
    input[5:0]       controlUnitCommand,
    input[5:0]       funct
);

    wire       WrEn_Reg1;
    wire       WrEn_DM1;
    wire[1:0]  WrAddr_Reg_Mux1;
    wire       ALU_input1;
    wire[2:0]  ALUcommand1;
    wire[1:0]  Reg_Data_Src_Mux1;
    wire       JumpR1;
    wire  Jump_Target_Mux1;
    wire       Branch1;

    wire       WrEn_Reg2;
    wire       WrEn_DM2;
    wire[1:0]  WrAddr_Reg_Mux2;
    wire       ALU_input2;
    wire[2:0]  ALUcommand2;
    wire[1:0]  Reg_Data_Src_Mux2;
    wire       JumpR2;
    wire  Jump_Target_Mux2;
    wire       Branch2;

    controlUnitLUT  lut_ctrl(WrEn_Reg1, WrEn_DM1, WrAddr_Reg_Mux1, ALU_input1, ALUcommand1,
                            Reg_Data_Src_Mux1, JumpR1, Jump_Target_Mux1, Branch1, controlUnitCommand, funct);

    R_type_LUT      R_ctrl(WrEn_Reg2, WrEn_DM2, WrAddr_Reg_Mux2, ALU_input2, ALUcommand2,
                            Reg_Data_Src_Mux2, JumpR2, Jump_Target_Mux2, Branch2, funct);

    always@* begin
        if (controlUnitCommand == 6'd0) begin
            WrEn_Reg <= WrEn_Reg2;
            WrEn_DM <= WrEn_DM2;
            WrAddr_Reg_Mux <= WrAddr_Reg_Mux2;
            ALU_input <= ALU_input2;
            ALUcommand <= ALUcommand2;
            Reg_Data_Src_Mux <= Reg_Data_Src_Mux2;
            JumpR <= JumpR2;
            Jump_Target_Mux <= Jump_Target_Mux2;
            Branch <= Branch2;
        end
        else begin
            WrEn_Reg <= WrEn_Reg1;
            WrEn_DM <= WrEn_DM1;
            WrAddr_Reg_Mux <= WrAddr_Reg_Mux1;
            ALU_input <= ALU_input1;
            ALUcommand <= ALUcommand1;
            Reg_Data_Src_Mux <= Reg_Data_Src_Mux1;
            JumpR <= JumpR1;
            Jump_Target_Mux <= Jump_Target_Mux1;
            Branch <= Branch1;
        end
    end

endmodule


module controlUnitLUT // Converts the commands to a more convenient format
(
    output reg       WrEn_Reg,
    output reg       WrEn_DM,
    output reg[1:0]  WrAddr_Reg_Mux,
    output reg       ALU_input,
    output reg[2:0]  ALUcommand,
    output reg[1:0]  Reg_Data_Src_Mux,
    output reg       JumpR,
    output reg       Jump_Target_Mux,
    output reg       Branch,
    input[5:0]       controlUnitCommand,
    input[5:0]       funct
);

    always @(controlUnitCommand) begin
      case (controlUnitCommand)
            `BNE:      begin WrEn_Reg = 0; WrEn_DM = 0; WrAddr_Reg_Mux = 0;    ALU_input = 1; ALUcommand = `SUB;    Reg_Data_Src_Mux = 0;      JumpR = 0; Jump_Target_Mux = 0; Branch = 1; end
            `LW:       begin WrEn_Reg = 1; WrEn_DM = 0; WrAddr_Reg_Mux = 0;    ALU_input = 0; ALUcommand = `ADD;    Reg_Data_Src_Mux = 0;      JumpR = 0; Jump_Target_Mux = 0; Branch = 0; end
            `SW:       begin WrEn_Reg = 0; WrEn_DM = 1; WrAddr_Reg_Mux = 0;    ALU_input = 0; ALUcommand = `ADD;    Reg_Data_Src_Mux = 0;      JumpR = 0; Jump_Target_Mux = 0; Branch = 0; end
            `J:        begin WrEn_Reg = 0; WrEn_DM = 0; WrAddr_Reg_Mux = 0;    ALU_input = 0; ALUcommand = `ADD;    Reg_Data_Src_Mux = 0;      JumpR = 0; Jump_Target_Mux = 1; Branch = 0; end
            `JAL:      begin WrEn_Reg = 1; WrEn_DM = 0; WrAddr_Reg_Mux = 2'd2; ALU_input = 0; ALUcommand = `ADD;    Reg_Data_Src_Mux = 2'd2;   JumpR = 0; Jump_Target_Mux = 1; Branch = 0; end
            // `XOR_c:    begin WrEn_Reg = 1; WrEn_DM = 0; WrAddr_Reg_Mux = 1;    ALU_input = 1; ALUcommand = `XOR;    Reg_Data_Src_Mux = 1;      JumpR = 0; Jump_Target_Mux = 0; Branch = 0; end
            `XOR_c:    begin WrEn_Reg = 1; WrEn_DM = 0; WrAddr_Reg_Mux = 0;    ALU_input = 1; ALUcommand = `XOR;    Reg_Data_Src_Mux = 1;      JumpR = 0; Jump_Target_Mux = 0; Branch = 0; end

        endcase
    end
endmodule

module R_type_LUT // Converts the commands to a more convenient format
(
    output reg       WrEn_Reg,
    output reg       WrEn_DM,
    output reg[1:0]  WrAddr_Reg_Mux,
    output reg       ALU_input,
    output reg[2:0]  ALUcommand,
    output reg[1:0]  Reg_Data_Src_Mux,
    output reg       JumpR,
    output reg       Jump_Target_Mux,
    output reg       Branch,
    input[5:0]       funct
);

    always @(funct) begin
      case (funct)
            `JR_c:      begin WrEn_Reg = 0; WrEn_DM = 0; WrAddr_Reg_Mux = 0; ALU_input = 0; ALUcommand = 6'd0;    Reg_Data_Src_Mux = 0;      JumpR = 1; Jump_Target_Mux = 1; Branch = 0; end
            `ADD_c:     begin WrEn_Reg = 1; WrEn_DM = 0; WrAddr_Reg_Mux = 1; ALU_input = 1; ALUcommand = `ADD;    Reg_Data_Src_Mux = 1;      JumpR = 0; Jump_Target_Mux = 0; Branch = 0; end
            `SUB_c:     begin WrEn_Reg = 1; WrEn_DM = 0; WrAddr_Reg_Mux = 1; ALU_input = 1; ALUcommand = `SUB;    Reg_Data_Src_Mux = 1;      JumpR = 0; Jump_Target_Mux = 0; Branch = 0; end
            `SLT_c:     begin WrEn_Reg = 1; WrEn_DM = 0; WrAddr_Reg_Mux = 1; ALU_input = 1; ALUcommand = `SLT;    Reg_Data_Src_Mux = 1;      JumpR = 0; Jump_Target_Mux = 0; Branch = 0; end
       endcase
    end
endmodule

control_unit_lut.t.v
//------------------------------------------------------------------------
// Control unit LUT test bnch
//------------------------------------------------------------------------
`timescale 1ns / 1ps

`include "control_unit_lut.v"

module testlut();

    wire        WrEn_Reg;
    wire        WrEn_DM;
    wire[1:0]   WrAddr_Reg_Mux;
    wire        ALU_input;
    wire[2:0]   ALUcommand;
    wire[1:0]   Reg_Data_Src_Mux;
    wire        Jump;
    wire        Jump_Target_Mux;
    wire        Branch;
    reg[5:0]    controlUnitCommand;
    reg[5:0]    funct;

    reg             dutpassed;


    // ALU Translation
    `define ADD  3'd0
    `define SUB  3'd1
    `define XOR  3'd2
    `define SLT  3'd3
    `define AND  3'd4
    `define NAND 3'd5
    `define NOR  3'd6
    `define OR   3'd7



    LUTcaller dut(WrEn_Reg, WrEn_DM, WrAddr_Reg_Mux,
                   ALU_input, ALUcommand, Reg_Data_Src_Mux,
                   Jump, Jump_Target_Mux, Branch, controlUnitCommand,
                   funct);

    initial begin
    	// Your Test Code
        $dumpfile("controlUnitLUT.vcd");
        $dumpvars();

        dutpassed = 1;

        #2
        // I type command testing
        funct = 6'd14; #1                //xor

        controlUnitCommand = 6'd05; #2 //bne
        if((ALU_input != 1'b1)||(Branch != 1'b1)
            ||(Jump != 1'b0)||(Jump_Target_Mux!=1'b0)||(Reg_Data_Src_Mux!=2'b00)
            ||(WrAddr_Reg_Mux!=2'b00)||(WrEn_DM!=1'b0)||(WrEn_Reg!=1'b0)
            ||(ALUcommand != `SUB)) begin
            dutpassed = 0;  // Set to 'false' on failure
            $display("Test Case 1 Failed: BNE implementation failed");
        end
        else begin
            $display("Test Case 1 Passed");
        end
        #1



        controlUnitCommand = 6'd35; #2 //lw
        if((ALU_input != 1'b0)||(Branch != 1'b0)
            ||(Jump != 1'b0)||(Jump_Target_Mux!=1'b0)||(Reg_Data_Src_Mux!=2'b00)
            ||(WrAddr_Reg_Mux!=2'b00)||(WrEn_DM!=1'b0)||(WrEn_Reg!=1'b1)) begin
            dutpassed = 0;  // Set to 'false' on failure
            $display("Test Case 2 Failed: LW implementation failed");
        end
        else begin
            $display("Test Case 2 Passed");
        end

        controlUnitCommand = 6'd43; #2 //sw
        if((ALU_input != 1'b0)||(Branch != 1'b0)
            ||(Jump != 1'b0)||(Jump_Target_Mux!=1'b0)||(Reg_Data_Src_Mux!=2'b00)
            ||(WrAddr_Reg_Mux!=2'b00)||(WrEn_DM!=1'b1)||(WrEn_Reg!=1'b0)) begin
            dutpassed = 0;  // Set to 'false' on failure
            $display("Test Case 3 Failed: SW implementation failed");
        end
        else begin
            $display("Test Case 3 Passed");
        end

        // J type testing
        controlUnitCommand = 6'd02; #2 //j
        if((ALU_input != 1'b0)||(Branch != 1'b0)
            ||(Jump != 1'b0)||(Jump_Target_Mux!=1'b1)||(Reg_Data_Src_Mux!=2'b00)
            ||(WrAddr_Reg_Mux!=2'b00)||(WrEn_DM!=1'b0)||(WrEn_Reg!=1'b0)) begin
            dutpassed = 0;  // Set to 'false' on failure
            $display("Test Case 4 Failed: J implementation failed");
        end
        else begin
            $display("Test Case 4 Passed");
        end

        controlUnitCommand = 6'd03; #2 //jal
        if((ALU_input != 1'b0)||(Branch != 1'b0)
            ||(Jump != 1'b0)||(Jump_Target_Mux!=1'b1)||(Reg_Data_Src_Mux!=2'b10)
            ||(WrAddr_Reg_Mux!=2'b10)||(WrEn_DM!=1'b0)||(WrEn_Reg!=1'b1)) begin
            dutpassed = 0;  // Set to 'false' on failure
            $display("Test Case 5 Failed: JAL implementation failed");
        end
        else begin
            $display("Test Case 5 Passed");
        end

        controlUnitCommand = 6'd14; #2                //xor
        if((ALU_input != 1'b1)||(Branch != 1'b0)
            ||(Jump != 1'b0)||(Jump_Target_Mux!=1'b0)||(Reg_Data_Src_Mux!=2'b01)
            ||(WrAddr_Reg_Mux!=2'b00)||(WrEn_DM!=1'b0)||(WrEn_Reg!=1'b1)
            ||(ALUcommand != 3'b010)) begin
            dutpassed = 0;  // Set to 'false' on failure
            $display("Test Case 6 Failed: XOR implementation failed");
        end
        else begin
            $display("Test Case 6 Passed");
        end

        // R type testing
        controlUnitCommand = 6'd00; //r type

        // R type funct testing
        funct = 6'd32; #2                //add
        if((ALU_input != 1'b1)||(Branch != 1'b0)
            ||(Jump != 1'b0)||(Jump_Target_Mux!=1'b0)||(Reg_Data_Src_Mux!=2'b01)
            ||(WrAddr_Reg_Mux!=2'b01)||(WrEn_DM!=1'b0)||(WrEn_Reg!=1'b1)
            ||(ALUcommand != `ADD)) begin
            dutpassed = 0;  // Set to 'false' on failure
            $display("Test Case 7 Failed: ADD implementation failed");
        end
        else begin
            $display("Test Case 7 Passed");
        end

        funct = 6'd34; #2                //sub
        if((ALU_input != 1'b1)||(Branch != 1'b0)
            ||(Jump != 1'b0)||(Jump_Target_Mux!=1'b0)||(Reg_Data_Src_Mux!=2'b01)
            ||(WrAddr_Reg_Mux!=2'b01)||(WrEn_DM!=1'b0)||(WrEn_Reg!=1'b1)
            ||(ALUcommand != `SUB)) begin
            dutpassed = 0;  // Set to 'false' on failure
            $display("Test Case 8 Failed: SUB implementation failed");
        end
        else begin
            $display("Test Case 8 Passed");
        end

        funct = 6'd42; #2                //slt
        if((ALU_input != 1'b1)||(Branch != 1'b0)
            ||(Jump != 1'b0)||(Jump_Target_Mux!=1'b0)||(Reg_Data_Src_Mux!=2'b01)
            ||(WrAddr_Reg_Mux!=2'b01)||(WrEn_DM!=1'b0)||(WrEn_Reg!=1'b1)
            ||(ALUcommand != `SLT)) begin
            dutpassed = 0;  // Set to 'false' on failure
            $display("Test Case 9 Failed: SLT implementation failed");
        end
        else begin
            $display("Test Case 9 Passed");
        end

        funct = 6'd8;  #2                //jr
        if((ALU_input != 1'b0)||(Branch != 1'b0)
            ||(Jump != 1'b1)||(Jump_Target_Mux!=1'b1)||(Reg_Data_Src_Mux!=2'b00)
            ||(WrAddr_Reg_Mux!=2'b00)||(WrEn_DM!=1'b0)||(WrEn_Reg!=1'b0)) begin
            dutpassed = 0;  // Set to 'false' on failure
            $display("Test Case 10 Failed: JR implementation failed");
        end
        else begin
            $display("Test Case 10 Passed");
        end
        $finish;
    end

endmodule

controlUnitLUT.vcd
$date
	Sun Nov 20 21:51:03 2016
$end
$version
	Icarus Verilog
$end
$timescale
	1ps
$end
$scope module testlut $end
$var wire 1 ! ALU_input $end
$var wire 3 " ALUcommand [2:0] $end
$var wire 1 # Branch $end
$var wire 1 $ Jump $end
$var wire 1 % Jump_Target_Mux $end
$var wire 2 & Reg_Data_Src_Mux [1:0] $end
$var wire 2 ' WrAddr_Reg_Mux [1:0] $end
$var wire 1 ( WrEn_DM $end
$var wire 1 ) WrEn_Reg $end
$var reg 6 * controlUnitCommand [5:0] $end
$var reg 1 + dutpassed $end
$var reg 6 , funct [5:0] $end
$scope module dut $end
$var wire 1 - ALU_input1 $end
$var wire 1 . ALU_input2 $end
$var wire 3 / ALUcommand1 [2:0] $end
$var wire 3 0 ALUcommand2 [2:0] $end
$var wire 1 1 Branch1 $end
$var wire 1 2 Branch2 $end
$var wire 1 3 JumpR1 $end
$var wire 1 4 JumpR2 $end
$var wire 1 5 Jump_Target_Mux1 $end
$var wire 1 6 Jump_Target_Mux2 $end
$var wire 2 7 Reg_Data_Src_Mux1 [1:0] $end
$var wire 2 8 Reg_Data_Src_Mux2 [1:0] $end
$var wire 2 9 WrAddr_Reg_Mux1 [1:0] $end
$var wire 2 : WrAddr_Reg_Mux2 [1:0] $end
$var wire 1 ; WrEn_DM1 $end
$var wire 1 < WrEn_DM2 $end
$var wire 1 = WrEn_Reg1 $end
$var wire 1 > WrEn_Reg2 $end
$var wire 6 ? controlUnitCommand [5:0] $end
$var wire 6 @ funct [5:0] $end
$var reg 1 A ALU_input $end
$var reg 3 B ALUcommand [2:0] $end
$var reg 1 C Branch $end
$var reg 1 D JumpR $end
$var reg 1 E Jump_Target_Mux $end
$var reg 2 F Reg_Data_Src_Mux [1:0] $end
$var reg 2 G WrAddr_Reg_Mux [1:0] $end
$var reg 1 H WrEn_DM $end
$var reg 1 I WrEn_Reg $end
$scope module lut_ctrl $end
$var wire 6 J controlUnitCommand [5:0] $end
$var wire 6 K funct [5:0] $end
$var reg 1 L ALU_input $end
$var reg 3 M ALUcommand [2:0] $end
$var reg 1 N Branch $end
$var reg 1 O JumpR $end
$var reg 1 P Jump_Target_Mux $end
$var reg 2 Q Reg_Data_Src_Mux [1:0] $end
$var reg 2 R WrAddr_Reg_Mux [1:0] $end
$var reg 1 S WrEn_DM $end
$var reg 1 T WrEn_Reg $end
$upscope $end
$scope module R_ctrl $end
$var wire 6 U funct [5:0] $end
$var reg 1 V ALU_input $end
$var reg 3 W ALUcommand [2:0] $end
$var reg 1 X Branch $end
$var reg 1 Y JumpR $end
$var reg 1 Z Jump_Target_Mux $end
$var reg 2 [ Reg_Data_Src_Mux [1:0] $end
$var reg 2 \ WrAddr_Reg_Mux [1:0] $end
$var reg 1 ] WrEn_DM $end
$var reg 1 ^ WrEn_Reg $end
$upscope $end
$upscope $end
$upscope $end
$enddefinitions $end
#0
$dumpvars
x^
x]
bx \
bx [
xZ
xY
xX
bx W
xV
bx U
xT
xS
bx R
bx Q
xP
xO
xN
bx M
xL
bx K
bx J
xI
xH
bx G
bx F
xE
xD
xC
bx B
xA
bx @
bx ?
x>
x=
x<
x;
bx :
bx 9
bx 8
bx 7
x6
x5
x4
x3
x2
x1
bx 0
bx /
x.
x-
bx ,
1+
bx *
x)
x(
bx '
bx &
x%
x$
x#
bx "
x!
$end
#2000
b1110 ,
b1110 @
b1110 K
b1110 U
#3000
1C
1#
0E
0%
0D
0$
b0 F
b0 &
b1 B
b1 "
1A
1!
b0 G
b0 '
0H
0(
0I
0)
1N
11
0P
05
0O
03
b0 Q
b0 7
b1 M
b1 /
1L
1-
b0 R
b0 9
0S
0;
0T
0=
b101 *
b101 ?
b101 J
#6000
0C
0#
b0 B
b0 "
0A
0!
1I
1)
0N
01
b0 M
b0 /
0L
0-
1T
1=
b100011 *
b100011 ?
b100011 J
#8000
1H
1(
0I
0)
1S
1;
0T
0=
b101011 *
b101011 ?
b101011 J
#10000
1E
1%
0H
0(
1P
15
0S
0;
b10 *
b10 ?
b10 J
#12000
b10 F
b10 &
b10 G
b10 '
1I
1)
b10 Q
b10 7
b10 R
b10 9
1T
1=
b11 *
b11 ?
b11 J
#14000
0E
0%
b1 F
b1 &
b10 B
b10 "
1A
1!
b0 G
b0 '
0P
05
b1 Q
b1 7
b10 M
b10 /
1L
1-
b0 R
b0 9
b1110 *
b1110 ?
b1110 J
#16000
0C
0#
0E
0%
0D
0$
b1 F
b1 &
b0 B
b0 "
1A
1!
b1 G
b1 '
0H
0(
1I
1)
0X
02
0Z
06
0Y
04
b1 [
b1 8
b0 W
b0 0
1V
1.
b1 \
b1 :
0]
0<
1^
1>
b100000 ,
b100000 @
b100000 K
b100000 U
b0 *
b0 ?
b0 J
#18000
b1 B
b1 "
b1 W
b1 0
b100010 ,
b100010 @
b100010 K
b100010 U
#20000
b11 B
b11 "
b11 W
b11 0
b101010 ,
b101010 @
b101010 K
b101010 U
#22000
1E
1%
1D
1$
b0 F
b0 &
b0 B
b0 "
0A
0!
b0 G
b0 '
0I
0)
1Z
16
1Y
14
b0 [
b0 8
b0 W
b0 0
0V
0.
b0 \
b0 :
0^
0>
b1000 ,
b1000 @
b1000 K
b1000 U
